{
  "transform": {
    ".(ts|tsx)": "<rootDir>/node_modules/ts-jest/preprocessor.js"
  },
  "testRegex": "(/__tests__/.*|\\.(test|spec))\\.(ts|tsx)$",
  "moduleFileExtensions": [
    "ts",
    "tsx",
    "js"
  ],
  "globals": {
    "__TS_CONFIG__": {
      "module": "commonjs",
      "jsx": "react",
      "experimentalDecorators": true,
      "emitDecoratorMetadata": true,
      "allowSyntheticDefaultImports": false,
      "moduleResolution": "node",
      "noEmitHelpers": true,
      "importHelpers": true
    }
  }
}